trialrumour2222/__init__.py
trialrumour2222/search_sort_array_algo.py
trialrumour2222-0.0.1.dist-info/METADATA
trialrumour2222-0.0.1.dist-info/WHEEL
trialrumour2222-0.0.1.dist-info/top_level.txt
trialrumour2222-0.0.1.dist-info/RECORD
