Metadata-Version: 2.1
Name: trialrumour2222
Version: 0.0.1
Summary: This package includes algorithms such as LinearSearch,BinarySearch, Two pointer , Sliding window. It will get updated every week!!!
Author: Rumour(Sarthak Samantaray)
Author-email: <sarthak.samantaraycoding@gmail.com>
License: UNKNOWN
Platform: UNKNOWN
